pubg_toolbox/__init__.py
pubg_toolbox/client.py
pubg_toolbox/constants/__init__.py
pubg_toolbox/constants/game.py
pubg_toolbox/data_types/__init__.py
pubg_toolbox/data_types/events.py
pubg_toolbox/data_types/queries.py
pubg_toolbox/data_types/types.py
pubg_toolbox-0.0.5.dist-info/LICENSE
pubg_toolbox-0.0.5.dist-info/METADATA
pubg_toolbox-0.0.5.dist-info/WHEEL
pubg_toolbox-0.0.5.dist-info/top_level.txt
pubg_toolbox-0.0.5.dist-info/RECORD
