Metadata-Version: 2.1
Name: pubg-toolbox
Version: 0.0.5
Summary: Simple queries and handles for PUBG data analysis
Home-page: https://github.com/junhan-z/pubg-toolbox
Author: Junhan Zhu
Author-email: junhanoct@gmail.com
License: UNKNOWN
Platform: UNKNOWN
Classifier: Programming Language :: Python :: 3
Classifier: License :: OSI Approved :: MIT License
Classifier: Topic :: Utilities
Requires-Python: >=3
